pucas/__init__.py
pucas/apps.py
pucas/cas_urls.py
pucas/ldap.py
pucas/signals.py
pucas/tests.py
pucas/management/__init__.py
pucas/management/commands/__init__.py
pucas/management/commands/createcasuser.py
pucas/management/commands/ldapsearch.py
pucas/static/pucas/pu-login.css
pucas/templates/pucas/cas-login.html
pucas/templates/pucas/pu-cas-login.html
pucas/templates/pucas/sample-admin-login.html
pucas/templates/pucas/sample-pu-login.html
pucas-0.9.1.dist-info/LICENSE
pucas-0.9.1.dist-info/METADATA
pucas-0.9.1.dist-info/WHEEL
pucas-0.9.1.dist-info/top_level.txt
pucas-0.9.1.dist-info/RECORD
