Metadata-Version: 2.1
Name: pucas
Version: 0.9.1
Summary: Django app to login with CAS and populate user accounts with LDAP.
Home-page: https://github.com/Princeton-CDH/django-pucas
Author: CDH @ Princeton
Author-email: digitalhumanities@princeton.edu
License: Apache License, Version 2.0
Classifier: Environment :: Web Environment
Classifier: Framework :: Django
Classifier: Framework :: Django :: 3.2
Classifier: Framework :: Django :: 4.0
Classifier: Framework :: Django :: 4.1
Classifier: Intended Audience :: Developers
Classifier: License :: OSI Approved :: Apache Software License
Classifier: Operating System :: OS Independent
Classifier: Programming Language :: Python
Classifier: Programming Language :: Python :: 3
Classifier: Programming Language :: Python :: 3.9
Classifier: Programming Language :: Python :: 3.10
Classifier: Programming Language :: Python :: 3.11
Classifier: Programming Language :: Python :: 3 :: Only
Classifier: Topic :: Internet :: WWW/HTTP
Classifier: Topic :: System :: Systems Administration :: Authentication/Directory
Classifier: Topic :: System :: Systems Administration :: Authentication/Directory :: LDAP
License-File: LICENSE
Requires-Dist: django >=1.8
Requires-Dist: django-cas-ng >=3.6
Requires-Dist: ldap3
Provides-Extra: test
Requires-Dist: pytest ; extra == 'test'
Requires-Dist: pytest-django ; extra == 'test'
Requires-Dist: pytest-cov ; extra == 'test'
